visio_json_export/__init__.py
visio_json_export/visio_model.py
visio_json_export-0.1.2.dist-info/LICENSE.txt
visio_json_export-0.1.2.dist-info/METADATA
visio_json_export-0.1.2.dist-info/WHEEL
visio_json_export-0.1.2.dist-info/RECORD
