Metadata-Version: 2.1
Name: visio-json-export
Version: 0.1.2
Summary: Helps to process Visio JSON Exports in your Python projects.
Home-page: https://geradeaus.engineering/
Author: Thomas Winkel
Author-email: mail@thomas-winkel.de
Requires-Python: >=3.12,<4.0
Classifier: License :: OSI Approved :: MIT License
Classifier: Operating System :: OS Independent
Classifier: Programming Language :: Python :: 3
Classifier: Programming Language :: Python :: 3.12
Classifier: Programming Language :: Python :: 3.13
Requires-Dist: pydantic (>=2.10.2,<3.0.0)
Project-URL: NuGet, https://www.nuget.org/packages/Geradeaus.VisioJsonExport
Project-URL: Repository, https://github.com/ThomasWinkel
